hello.py
hello_bouk-0.0.1.data/scripts/hello
hello_bouk-0.0.1.dist-info/LICENSE
hello_bouk-0.0.1.dist-info/METADATA
hello_bouk-0.0.1.dist-info/WHEEL
hello_bouk-0.0.1.dist-info/top_level.txt
hello_bouk-0.0.1.dist-info/RECORD
